prun/__init__.py
prun-0.3.1.dist-info/LICENSE
prun-0.3.1.dist-info/METADATA
prun-0.3.1.dist-info/WHEEL
prun-0.3.1.dist-info/entry_points.txt
prun-0.3.1.dist-info/top_level.txt
prun-0.3.1.dist-info/RECORD
