Metadata-Version: 2.1
Name: prun
Version: 0.3.1
Summary: A convenience app for working with virtual environments like a breeze.
Home-page: https://github.com/PeterPyPan/prun
Author: PeterPyPan
Author-email: PeterPyPanGitHub@gmail.com
License: MIT
Keywords: virtual environment venv .venv virtualenv pipenv
Platform: UNKNOWN
Classifier: Development Status :: 4 - Beta
Classifier: Intended Audience :: Developers
Classifier: Topic :: Software Development :: Build Tools
Classifier: License :: OSI Approved :: MIT License
Classifier: Programming Language :: Python :: 3
Requires-Python: >=3
Provides-Extra: dev
Requires-Dist: pytest ; extra == 'dev'
